[
    {
        "id": 1,
        "usuario": "congue",
        "email": "dhellen0@google.com",
        "password": "dM1(lk%gA7&p7",
        "foto": "/images/avatars/avatar-default.jpg"
    },
    {
        "id": 2,
        "usuario": "vulputate",
        "email": "bminall1@nydailynews.com",
        "password": "hO3<|Up0",
        "foto": "/images/avatars/avatar-default.jpg"
    },
    {
        "id": 3,
        "usuario": "agustin",
        "email": "agustinramirez58@gmail.com",
        "foto": "/images/avatars/avatar-default.jpg",
        "password": "$2a$10$HK0BAohRNXhfFgHWzcMKhOpzb1STm0CONpdiQPoNUWnmWSiAGs18C"
    }
]